detox/__init__.py
detox/functional.py
detox/metric.py
detox/shim.py
detox/util.py
detox/attack/__init__.py
detox/attack/atn.py
detox/attack/attack.py
detox/attack/basic_iterative.py
detox/attack/boundary.py
detox/attack/carlini_wagner.py
detox/attack/deep_fool.py
detox/attack/feature_adversaries.py
detox/attack/fgm.py
detox/attack/functional.py
detox/attack/jsma.py
detox/attack/lbfgs.py
detox/attack/momentum_iterative.py
detox/attack/nae.py
detox/attack/one_pixel.py
detox/attack/uap.py
detox/nn/__init__.py
detox/nn/autoencoder.py
detox/nn/wgan.py
dtox-0.1.0.dist-info/METADATA
dtox-0.1.0.dist-info/RECORD
dtox-0.1.0.dist-info/WHEEL
dtox-0.1.0.dist-info/top_level.txt
